jhu_assembly_linter/cmd.py
jhu_assembly_linter/finding.py
jhu_assembly_linter/linter.py
jhu_assembly_linter-0.1.7.dist-info/METADATA
jhu_assembly_linter-0.1.7.dist-info/WHEEL
jhu_assembly_linter-0.1.7.dist-info/entry_points.txt
jhu_assembly_linter-0.1.7.dist-info/RECORD
