Metadata-Version: 2.1
Name: jhu-assembly-linter
Version: 0.1.7
Summary: A Linter for JHU's Assembly Classes
Home-page: https://pypi.org/project/jhu-assembly-linter/
License: MIT
Keywords: jhu,assembly,linter
Author: Paul Logston
Author-email: pbulkle1@jh.edu
Maintainer: Paul Logston
Maintainer-email: pbulkle1@jh.edu
Requires-Python: >=3.9
Classifier: Intended Audience :: Developers
Classifier: License :: OSI Approved :: MIT License
Classifier: Natural Language :: English
Classifier: Operating System :: OS Independent
Classifier: Programming Language :: Python :: 3
Classifier: Programming Language :: Python :: 3.9
Classifier: Programming Language :: Python :: 3.10
Classifier: Programming Language :: Python :: 3.11
Project-URL: Repository, https://github.com/LogstonGradSchool/JhuAssemblyStyleLinter
